mlscorer/__init__.py
mlscorer-0.3.dist-info/LICENSE
mlscorer-0.3.dist-info/METADATA
mlscorer-0.3.dist-info/WHEEL
mlscorer-0.3.dist-info/top_level.txt
mlscorer-0.3.dist-info/RECORD
