Metadata-Version: 2.1
Name: mlscorer
Version: 0.3
Summary: UNKNOWN
Home-page: UNKNOWN
Author: Avishek Das
Author-email: avishek.das.ayan@gmail.com
License: MIT
Platform: UNKNOWN
Classifier: Programming Language :: Python :: 3
Classifier: License :: OSI Approved :: MIT License
Classifier: Operating System :: OS Independent
Requires-Dist: prettytable
Requires-Dist: scikit-learn
